d3m/__init__.py
d3m/__main__.py
d3m/cli.py
d3m/deprecate.py
d3m/environment_variables.py
d3m/exceptions.py
d3m/index.py
d3m/metrics.py
d3m/namespace.py
d3m/py.typed
d3m/runtime.py
d3m/types.py
d3m/utils.py
d3m/base/__init__.py
d3m/base/primitives.py
d3m/base/utils.py
d3m/container/__init__.py
d3m/container/dataset.py
d3m/container/list.py
d3m/container/numpy.py
d3m/container/pandas.py
d3m/container/utils.py
d3m/contrib/__init__.py
d3m/contrib/openml/__init__.py
d3m/contrib/openml/crawler.py
d3m/contrib/pipelines/3c11d171-e2ad-4d26-a034-04f3b062306c.yml
d3m/contrib/pipelines/79ce71bd-db96-494b-a455-14f2e2ac5040.yml
d3m/contrib/pipelines/9c18472e-fff7-4129-93f6-1ab996e82adb.yml
d3m/contrib/pipelines/__init__.py
d3m/contrib/pipelines/c8ed65df-aa68-4ee0-bbb5-c5f76a40bcf8.yml
d3m/contrib/pipelines/f596cd77-25f8-4d4c-a350-bb30ab1e58f6.yml
d3m/contrib/primitives/__init__.py
d3m/contrib/primitives/base.py
d3m/contrib/primitives/compute_scores.py
d3m/contrib/primitives/null.py
d3m/metadata/__init__.py
d3m/metadata/base.py
d3m/metadata/hyperparams.py
d3m/metadata/params.py
d3m/metadata/pipeline.py
d3m/metadata/pipeline_run.py
d3m/metadata/primitive_names.py
d3m/metadata/problem.py
d3m/metadata/schemas/v0/container.json
d3m/metadata/schemas/v0/data.json
d3m/metadata/schemas/v0/definitions.json
d3m/metadata/schemas/v0/pipeline.json
d3m/metadata/schemas/v0/pipeline_run.json
d3m/metadata/schemas/v0/primitive.json
d3m/metadata/schemas/v0/problem.json
d3m/primitive_interfaces/__init__.py
d3m/primitive_interfaces/base.py
d3m/primitive_interfaces/clustering.py
d3m/primitive_interfaces/distance.py
d3m/primitive_interfaces/featurization.py
d3m/primitive_interfaces/generator.py
d3m/primitive_interfaces/supervised_learning.py
d3m/primitive_interfaces/transformer.py
d3m/primitive_interfaces/unsupervised_learning.py
d3m-2022.5.5.dist-info/LICENSE.txt
d3m-2022.5.5.dist-info/METADATA
d3m-2022.5.5.dist-info/WHEEL
d3m-2022.5.5.dist-info/entry_points.txt
d3m-2022.5.5.dist-info/top_level.txt
d3m-2022.5.5.dist-info/RECORD
