Metadata-Version: 2.1
Name: d3m
Version: 2022.5.5
Summary: project
Home-page: https://gitlab.com/datadrivendiscovery/d3m
Author: Program
License: Apache-2.0
Platform: UNKNOWN
Classifier: License :: OSI Approved :: Apache Software License
Requires-Dist: GitPython (<3.2,>=3.1.0)
Requires-Dist: PyYAML (<5.5,>=5.1)
Requires-Dist: custom-inherit (<2.4,>=2.2.0)
Requires-Dist: dateparser (<1.2.0,>=0.7.0)
Requires-Dist: frozendict (<1.3,>=1.2)
Requires-Dist: gputil (<1.5,>=1.3.0)
Requires-Dist: jsonpath-ng (<1.6,>=1.4.3)
Requires-Dist: jsonschema (<4.1,>=3.0.2)
Requires-Dist: numpy (<1.22,>=1.16.6)
Requires-Dist: openml (<0.12,>=0.11.0)
Requires-Dist: pandas (<1.4,>=1.1.3)
Requires-Dist: pyrsistent (<0.19,>=0.14.11)
Requires-Dist: python-dateutil (<2.9,>=2.8.1)
Requires-Dist: pytypes (==1.0b10)
Requires-Dist: requests (<2.27,>=2.19.1)
Requires-Dist: rfc3339-validator (<0.2,>=0.1)
Requires-Dist: rfc3986-validator (<0.2,>=0.1)
Requires-Dist: scikit-learn (<0.25,>=0.21.3)
Requires-Dist: scipy (<1.8,>=1.2.1)
Requires-Dist: typing-inspect (==0.7.1)
Requires-Dist: webcolors (<1.12,>=1.8.1)
Provides-Extra: tests
Requires-Dist: asv (==0.4.2) ; extra == 'tests'
Requires-Dist: docker[tls] (<6,>=5.0) ; extra == 'tests'
